[{"uid":"blt75855d1d1dca31e5","content_type":"image/png","file_size":"64021","tags":[],"filename":"blogs.png","url":"https://images.contentstack.io/v3/assets/blt90575446cdf5e249/blt75855d1d1dca31e5/5f86ddf318cd5f0f67ac2a4a/blogs.png","ACL":{},"is_dir":false,"parent_uid":null,"_version":1,"title":"blogs.png","publish_details":[{"environment":"blt4c34b63722dfd30d","locale":"en-us","time":"2020-10-14T11:16:04.536Z","user":"bltf01cfddcefa2394d","version":1},{"environment":"bltf8b8247446de82b3","locale":"en-us","time":"2020-10-14T11:16:04.536Z","user":"bltf01cfddcefa2394d","version":1}]}]